setup.py
distributions/Binomialdistribution.py
distributions/Gaussiandistribution.py
distributions/Generaldistribution.py
distributions/__init__.py
whodan_prob.egg-info/PKG-INFO
whodan_prob.egg-info/SOURCES.txt
whodan_prob.egg-info/dependency_links.txt
whodan_prob.egg-info/not-zip-safe
whodan_prob.egg-info/top_level.txt